ragas/__init__.py
ragas/_analytics.py
ragas/_version.py
ragas/async_utils.py
ragas/cache.py
ragas/callbacks.py
ragas/cli.py
ragas/config.py
ragas/cost.py
ragas/dataset.py
ragas/dataset_schema.py
ragas/evaluation.py
ragas/exceptions.py
ragas/executor.py
ragas/experiment.py
ragas/losses.py
ragas/messages.py
ragas/py.typed
ragas/run_config.py
ragas/sdk.py
ragas/utils.py
ragas/validation.py
ragas/backends/README.md
ragas/backends/__init__.py
ragas/backends/base.py
ragas/backends/gdrive_backend.md
ragas/backends/gdrive_backend.py
ragas/backends/inmemory.py
ragas/backends/local_csv.py
ragas/backends/local_jsonl.py
ragas/backends/registry.py
ragas/backends/utils.py
ragas/embeddings/__init__.py
ragas/embeddings/base.py
ragas/embeddings/google_provider.py
ragas/embeddings/haystack_wrapper.py
ragas/embeddings/huggingface_provider.py
ragas/embeddings/litellm_provider.py
ragas/embeddings/openai_provider.py
ragas/embeddings/utils.py
ragas/integrations/__init__.py
ragas/integrations/amazon_bedrock.py
ragas/integrations/griptape.py
ragas/integrations/helicone.py
ragas/integrations/langchain.py
ragas/integrations/langgraph.py
ragas/integrations/langsmith.py
ragas/integrations/llama_index.py
ragas/integrations/opik.py
ragas/integrations/r2r.py
ragas/integrations/swarm.py
ragas/integrations/tracing/__init__.py
ragas/integrations/tracing/langfuse.py
ragas/integrations/tracing/mlflow.py
ragas/llms/__init__.py
ragas/llms/base.py
ragas/llms/haystack_wrapper.py
ragas/llms/oci_genai_wrapper.py
ragas/metrics/__init__.py
ragas/metrics/_answer_correctness.py
ragas/metrics/_answer_relevance.py
ragas/metrics/_answer_similarity.py
ragas/metrics/_aspect_critic.py
ragas/metrics/_bleu_score.py
ragas/metrics/_chrf_score.py
ragas/metrics/_context_entities_recall.py
ragas/metrics/_context_precision.py
ragas/metrics/_context_recall.py
ragas/metrics/_datacompy_score.py
ragas/metrics/_domain_specific_rubrics.py
ragas/metrics/_factual_correctness.py
ragas/metrics/_faithfulness.py
ragas-0.3.6.dist-info/licenses/LICENSE
ragas-0.3.6.dist-info/METADATA
ragas-0.3.6.dist-info/WHEEL
ragas-0.3.6.dist-info/entry_points.txt
ragas-0.3.6.dist-info/top_level.txt
ragas-0.3.6.dist-info/RECORD
