Metadata-Version: 2.4
Name: ragas
Version: 0.3.6
Summary: Evaluation framework for RAG and LLM applications
License:                                  Apache License
Project-URL: Homepage, https://github.com/explodinggradients/ragas
Project-URL: Documentation, https://docs.ragas.io
Project-URL: Code, https://github.com/explodinggradients/ragas
Project-URL: Issues, https://github.com/explodinggradients/ragas/issues
Requires-Python: >=3.9
License-File: LICENSE
Requires-Dist: numpy<3.0.0,>=1.21.0
Requires-Dist: datasets>=4.0.0
Requires-Dist: tiktoken
Requires-Dist: pydantic>=2.0.0
Requires-Dist: nest-asyncio
Requires-Dist: appdirs
Requires-Dist: diskcache>=5.6.3
Requires-Dist: typer
Requires-Dist: rich
Requires-Dist: openai>=1.0.0
Requires-Dist: tqdm
Requires-Dist: instructor
Requires-Dist: gitpython
Requires-Dist: pillow>=10.4.0
Requires-Dist: networkx
Requires-Dist: scikit-network
Requires-Dist: langchain
Requires-Dist: langchain-core
Requires-Dist: langchain-community
Requires-Dist: langchain_openai
Provides-Extra: all
Requires-Dist: sentence-transformers; extra == "all"
Requires-Dist: transformers; extra == "all"
Requires-Dist: nltk; extra == "all"
Requires-Dist: rouge_score; extra == "all"
Requires-Dist: rapidfuzz; extra == "all"
Requires-Dist: pandas; extra == "all"
Requires-Dist: datacompy; extra == "all"
Requires-Dist: sacrebleu; extra == "all"
Requires-Dist: llama_index; extra == "all"
Requires-Dist: r2r; extra == "all"
Provides-Extra: tracing
Requires-Dist: langfuse>=3.2.4; extra == "tracing"
Requires-Dist: mlflow>=3.1.4; extra == "tracing"
Provides-Extra: gdrive
Requires-Dist: google-api-python-client>=2.178.0; extra == "gdrive"
Requires-Dist: google-auth>=2.40.3; extra == "gdrive"
Requires-Dist: google-auth-oauthlib>=1.2.2; extra == "gdrive"
Provides-Extra: ai-frameworks
Requires-Dist: haystack-ai; extra == "ai-frameworks"
Provides-Extra: oci
Requires-Dist: oci>=2.160.1; extra == "oci"
Provides-Extra: dev-minimal
Requires-Dist: ruff; extra == "dev-minimal"
Requires-Dist: pyright>=1.1.403; extra == "dev-minimal"
Requires-Dist: pre-commit>=4.3.0; extra == "dev-minimal"
Requires-Dist: pytest; extra == "dev-minimal"
Requires-Dist: pytest-xdist[psutil]; extra == "dev-minimal"
Requires-Dist: pytest-asyncio; extra == "dev-minimal"
Requires-Dist: nbmake; extra == "dev-minimal"
Requires-Dist: build>=1.3.0; extra == "dev-minimal"
Provides-Extra: test
Requires-Dist: scipy; extra == "test"
Dynamic: license-file
